human_json/__init__.py
human_json/transformer.py
human_json-0.3.0.dist-info/LICENSE
human_json-0.3.0.dist-info/WHEEL
human_json-0.3.0.dist-info/METADATA
human_json-0.3.0.dist-info/RECORD
