Metadata-Version: 2.1
Name: human-json
Version: 0.3.0
Summary: Transform JSON Objects to human readable strings
Home-page: https://github.com/jakubclark/human-json
License: MIT
Keywords: json,pretty,human
Author: Kuba Clark
Author-email: jakub.clark@protonmail.com
Requires-Python: >=3.6,<4.0
Classifier: License :: OSI Approved :: MIT License
Classifier: Programming Language :: Python :: 3
Classifier: Programming Language :: Python :: 3.6
Classifier: Programming Language :: Python :: 3.7
Project-URL: Repository, https://github.com/jakubclark/human-json
